django_glitter_documents-0.2.11.dist-info/METADATA
django_glitter_documents-0.2.11.dist-info/RECORD
django_glitter_documents-0.2.11.dist-info/WHEEL
django_glitter_documents-0.2.11.dist-info/top_level.txt
glitter_documents/__init__.py
glitter_documents/admin.py
glitter_documents/apps.py
glitter_documents/mixins.py
glitter_documents/models.py
glitter_documents/search_indexes.py
glitter_documents/urls.py
glitter_documents/views.py
glitter_documents/migrations/0001_initial.py
glitter_documents/migrations/0002_document_tags.py
glitter_documents/migrations/0003_category_parent_category.py
glitter_documents/migrations/0004_add_field_publish_at.py
glitter_documents/migrations/0005_copy_date_created_to_publish.py
glitter_documents/migrations/0006_document_image.py
glitter_documents/migrations/__init__.py
glitter_documents/templates/glitter/blocks/latestdocumentsblock.html
glitter_documents/templates/search/indexes/glitter_documents/document_text.txt
glitter_documents/templatetags/__init__.py
glitter_documents/templatetags/documents_tags.py
